aitestflow/__init__.py
aitestflow-0.0.1.dist-info/LICENSE
aitestflow-0.0.1.dist-info/METADATA
aitestflow-0.0.1.dist-info/WHEEL
aitestflow-0.0.1.dist-info/top_level.txt
aitestflow-0.0.1.dist-info/RECORD
