Metadata-Version: 2.1
Name: aitestflow
Version: 0.0.1
Summary: aitestflow is a Python package used for creating automated test scripts for all types of applications. 
Home-page: https://github.com/WIINAI-KKUMAR/aitestflow
Author: Vinaykumar Puppala
Author-email: vinaykumar.puppala@outlook.com
License: UNKNOWN
Platform: UNKNOWN
Classifier: Programming Language :: Python :: 3
Classifier: License :: OSI Approved :: MIT License
Classifier: Operating System :: OS Independent
Requires-Dist: pytest-parallel
Requires-Dist: pytest-xdist
Requires-Dist: pandas
Requires-Dist: azure-devops (==5.0.0b9)
Requires-Dist: selenium (==3.141.0)
Requires-Dist: requests
Requires-Dist: cx-oracle
Requires-Dist: pymssql
Requires-Dist: mysql-connector (==2.2.9)
Requires-Dist: jsonpath
Requires-Dist: pytest
Requires-Dist: xlrd
Requires-Dist: XlsxWriter
Requires-Dist: cryptography
Requires-Dist: tabulate
Requires-Dist: pysftp
Requires-Dist: jaydebeapi (==1.2.3)
Requires-Dist: elasticsearch (==7.6.0)
Requires-Dist: chardet
Requires-Dist: msedge-selenium-tools
Requires-Dist: datacompy
Requires-Dist: Appium-Python-Client
Requires-Dist: webdriver-manager
Requires-Dist: junit-xml
